pyntload/__init__.py
pyntload/helper.py
pyntload/pyntload.py
pyntload-0.3.8.dist-info/METADATA
pyntload-0.3.8.dist-info/WHEEL
pyntload-0.3.8.dist-info/licenses/LICENSE.txt
pyntload-0.3.8.dist-info/RECORD
